{
  "actions": [
    {
      "type": "deleteTable",
      "deleteTable": "password_update_request"
    },
    {
      "type": "createTable",
      "createTable": {
        "name": "password_update",
        "dartName": "PasswordUpdate",
        "module": "notes",
        "schema": "public",
        "columns": [
          {
            "name": "id",
            "columnType": 2,
            "isNullable": false,
            "columnDefault": "nextval('password_update_id_seq'::regclass)",
            "dartType": "int?"
          },
          {
            "name": "userId",
            "columnType": 2,
            "isNullable": false,
            "dartType": "int"
          },
          {
            "name": "validationCodeId",
            "columnType": 2,
            "isNullable": false,
            "dartType": "int"
          }
        ],
        "foreignKeys": [
          {
            "constraintName": "password_update_fk_0",
            "columns": [
              "userId"
            ],
            "referenceTable": "serverpod_user_info",
            "referenceTableSchema": "public",
            "referenceColumns": [
              "id"
            ],
            "onUpdate": 3,
            "onDelete": 3
          },
          {
            "constraintName": "password_update_fk_1",
            "columns": [
              "validationCodeId"
            ],
            "referenceTable": "validation_code",
            "referenceTableSchema": "public",
            "referenceColumns": [
              "id"
            ],
            "onUpdate": 3,
            "onDelete": 3
          }
        ],
        "indexes": [
          {
            "indexName": "password_update_pkey",
            "elements": [
              {
                "type": 0,
                "definition": "id"
              }
            ],
            "type": "btree",
            "isUnique": true,
            "isPrimary": true
          },
          {
            "indexName": "password_request__user_id__unique_idx",
            "elements": [
              {
                "type": 0,
                "definition": "userId"
              }
            ],
            "type": "btree",
            "isUnique": true,
            "isPrimary": false
          }
        ],
        "managed": true
      }
    }
  ],
  "warnings": [
    {
      "type": "tableDropped",
      "message": "Table \"password_update_request\" will be dropped.",
      "table": "password_update_request",
      "columns": [],
      "destrucive": true
    }
  ],
  "migrationApiVersion": 1
}